{
  "project_info": {
    "project_number": "87510298828",
    "project_id": "cscb07grp8",
    "storage_bucket": "cscb07grp8.appspot.com"
  },
  "client": [
    {
      "client_info": {
        "mobilesdk_app_id": "1:87510298828:android:a2d61471d3b45a07549269",
        "android_client_info": {
          "package_name": "com.example.myfirstapp"
        }
      },
      "oauth_client": [
        {
          "client_id": "87510298828-k0olcoj1aekc84lt0knqlqbf706q56n4.apps.googleusercontent.com",
          "client_type": 3
        }
      ],
      "api_key": [
        {
          "current_key": "AIzaSyCvu3KT3LU6kDm1HzIa7NFJifEFFKq9jFs"
        }
      ],
      "services": {
        "appinvite_service": {
          "other_platform_oauth_client": [
            {
              "client_id": "87510298828-k0olcoj1aekc84lt0knqlqbf706q56n4.apps.googleusercontent.com",
              "client_type": 3
            }
          ]
        }
      }
    }
  ],
  "configuration_version": "1"
}